[
  {
    "name": "Administrator",
    "icon": "verified",
    "description": "$t:admin_description",
    "parent": null,
    "_syncId": "_sync_default_admin_role"
  },
  {
    "name": "Content editor",
    "icon": "accessibility",
    "description": "Can edit all content",
    "parent": null,
    "_syncId": "7eaeec22-d277-4263-94e7-93c0d213c61e"
  },
  {
    "name": "Static site generator",
    "icon": "construction",
    "description": "Can read minimal resources to build a static website",
    "parent": null,
    "_syncId": "ca19ad52-f640-4f9b-be7a-cd8a393b83de"
  }
]
